{
  "hash": "36245c7e",
  "configHash": "96de728a",
  "lockfileHash": "4c87ebe0",
  "browserHash": "6336a871",
  "optimized": {
    "react": {
      "src": "../../node_modules/react/index.js",
      "file": "react.js",
      "fileHash": "c675a024",
      "needsInterop": true
    },
    "zustand": {
      "src": "../../node_modules/zustand/esm/index.mjs",
      "file": "zustand.js",
      "fileHash": "bf8300d5",
      "needsInterop": false
    },
    "uuid": {
      "src": "../../node_modules/uuid/dist/index.js",
      "file": "uuid.js",
      "fileHash": "479ca403",
      "needsInterop": false
    },
    "react-dom/client": {
      "src": "../../node_modules/react-dom/client.js",
      "file": "react-dom_client.js",
      "fileHash": "34c730a7",
      "needsInterop": true
    }
  },
  "chunks": {
    "chunk-HWMK2RSU": {
      "file": "chunk-HWMK2RSU.js"
    },
    "chunk-5WRI5ZAA": {
      "file": "chunk-5WRI5ZAA.js"
    }
  }
}